qerent_keyring/__init__.py
qerent_keyring/plugin.py
qerent_keyring-0.1.0.dist-info/licenses/LICENSE
qerent_keyring-0.1.0.dist-info/METADATA
qerent_keyring-0.1.0.dist-info/WHEEL
qerent_keyring-0.1.0.dist-info/entry_points.txt
qerent_keyring-0.1.0.dist-info/top_level.txt
qerent_keyring-0.1.0.dist-info/RECORD
