Metadata-Version: 2.4
Name: qerent-keyring
Version: 0.1.0
Summary: "Automatically retrieve credentials for Qerent Distribution."
Author: Qerent
License: "Other/Proprietary"
Classifier: Development Status :: 3 - Alpha
Classifier: Intended Audience :: Developers
Classifier: Programming Language :: Python :: 3.9
Classifier: Programming Language :: Python :: 3.10
Classifier: Programming Language :: Python :: 3.11
Classifier: Programming Language :: Python :: 3.12
Classifier: Programming Language :: Python :: 3.13
Classifier: Operating System :: Microsoft :: Windows
Classifier: Operating System :: POSIX :: Linux
Requires-Python: >=3.9
License-File: LICENSE
Requires-Dist: keyring>=22.0
Requires-Dist: requests>=2.20.0
Dynamic: license-file
